loci_sarif/__init__.py
loci_sarif/add.py
loci_sarif/main.py
loci_sarif/summary.py
loci_sarif/utils.py
loci_sarif-0.3.1.dist-info/LICENSE
loci_sarif-0.3.1.dist-info/METADATA
loci_sarif-0.3.1.dist-info/WHEEL
loci_sarif-0.3.1.dist-info/entry_points.txt
loci_sarif-0.3.1.dist-info/top_level.txt
loci_sarif-0.3.1.dist-info/RECORD
