Metadata-Version: 2.1
Name: loci-sarif
Version: 0.3.1
Summary: The official Loci Notes SARIF processor.
Home-page: https://gitlab.com/loci-notes/loci-sarif
Author: TheTwitchy
Author-email: thetwitchy@thetwitchy.com
License-File: LICENSE
Requires-Dist: loci-cli (>=0.10.1)
